{
	"about":{
		"width":1000,
		"height":340
	},
	"projectSetting":{
		"width":300,
		"height":180
	},
	"preference":{
		"width":800,
		"height":300
	},
	"udoWizard":{
		"width":800,
		"height":540
	},
	
	"boardManager":{
		"width":600,
		"height":270
	},
	"libraryManager":{
		"width":600,
		"height":270
	},
	"libraryVersion":{
		"width":500,
		"height":150
	},
	"connectedBoard":{
		"width":600,
		"height":160
	},
	"port":{
		"width":550,
		"height":160
	},
	"board":{
		"width":350,
		"height":150
	},
	"messageWindow":{
		"width":200,
		"height":25
	}
}